cyberarkgetpassword/__init__.py
cyberarkgetpassword/cyberark_get_password_obj.py
cyberarkgetpassword-0.1.1.dist-info/METADATA
cyberarkgetpassword-0.1.1.dist-info/WHEEL
cyberarkgetpassword-0.1.1.dist-info/top_level.txt
cyberarkgetpassword-0.1.1.dist-info/RECORD
