Metadata-Version: 2.1
Name: cyberarkgetpassword
Version: 0.1.1
Summary: Utility to fetch CyberArk passwords
Home-page: https://github.com/yourusername/cyberarkgetpassword
Author: Surendra Kumar
Author-email: your_email@example.com
Classifier: Programming Language :: Python :: 3
Classifier: Operating System :: OS Independent
Requires-Python: >=3.6
